data_il_fetcher/__init__.py
data_il_fetcher/common.py
data_il_fetcher/nadlan.py
data_il_fetcher/yad2.py
data_il_fetcher-1.0.2.dist-info/METADATA
data_il_fetcher-1.0.2.dist-info/WHEEL
data_il_fetcher-1.0.2.dist-info/licenses/LICENSE
data_il_fetcher-1.0.2.dist-info/RECORD
